vcore/Vcore.py
vcore/__init__.py
vcore/constants.py
vcore/abi/__init__.py
vcore/abi/chainlink.py
vcore/abi/comptroller.py
vcore/abi/init_abi.py
vcore/abi/pool_abi.py
vcore/abi/pool_abi2.py
vcore/abi/vBNB.py
vcore/abi/vToken.py
vcore/abi/venusLens.py
vcore-0.3.0.dist-info/METADATA
vcore-0.3.0.dist-info/WHEEL
vcore-0.3.0.dist-info/top_level.txt
vcore-0.3.0.dist-info/RECORD
